pkgconf/__init__.py
pkgconf/__main__.py
pkgconf/_path_entrypoints.py
pkgconf/diagnose.py
pkgconf/py.typed
pkgconf/.bin/pkgconf
pkgconf-2.5.1.post0.dist-info/LICENSE
pkgconf-2.5.1.post0.dist-info/METADATA
pkgconf-2.5.1.post0.dist-info/WHEEL
pkgconf-2.5.1.post0.dist-info/entry_points.txt
pkgconf-2.5.1.post0.dist-info/RECORD
