Metadata-Version: 2.1
Name: pkgconf
Version: 2.5.1.post0
Summary: `pkgconf` is a program which helps with discovering library dependencies and configuring compiler and linker flags.
Author-Email: Ralf Gommers <ralf.gommers@gmail.com>, =?utf-8?q?Filipe_La=C3=ADns?= <lains@riseup.net>
License: Copyright (c) 2024 pypackaging-native contributors
Classifier: Development Status :: 4 - Beta
Classifier: Intended Audience :: Developers
Classifier: License :: OSI Approved :: MIT License
Classifier: License :: OSI Approved :: ISC License (ISCL)
Classifier: Programming Language :: C
Classifier: Topic :: Software Development
Classifier: Operating System :: Microsoft :: Windows
Classifier: Operating System :: POSIX
Classifier: Operating System :: Unix
Classifier: Operating System :: MacOS
Project-URL: homepage, https://pkgconf-pypi.readthedocs.io/en/latest/
Project-URL: issues, https://github.com/pypackaging-native/pkgconf-pypi/issues
Project-URL: source, https://github.com/pypackaging-native/pkgconf-pypi
Requires-Python: >=3.10
Requires-Dist: colorama; os_name == "nt"
Provides-Extra: test
Requires-Dist: pytest; extra == "test"
Requires-Dist: pytest-cov>=5; extra == "test"
Requires-Dist: pytest-mock>=2; extra == "test"
Requires-Dist: pytest-order>=1; extra == "test"
Requires-Dist: pytest-github-actions-annotate-failures; extra == "test"
Requires-Dist: meson-python; extra == "test"
Requires-Dist: environment-helpers>=0.1.3; extra == "test"
Provides-Extra: docs
Requires-Dist: sphinx~=7.0; extra == "docs"
Requires-Dist: furo; extra == "docs"
Requires-Dist: sphinx-design; extra == "docs"
